physical_units/__init__.py
physical_units/base.py
physical_units/const.py
physical_units/time.py
physical_units-0.0.1.dist-info/WHEEL
physical_units-0.0.1.dist-info/METADATA
physical_units-0.0.1.dist-info/RECORD
